README.rst
setup.py
domain_cdate/__init__.py
domain_cdate/data.py
domain_cdate.egg-info/PKG-INFO
domain_cdate.egg-info/SOURCES.txt
domain_cdate.egg-info/dependency_links.txt
domain_cdate.egg-info/top_level.txt