Metadata-Version: 1.0
Name: domain-cdate
Version: 0.1.0
Summary: Domain creation date extractor
Home-page: https://github.com/nibrag/domain_cdate
Author: Nail Ibragimov
Author-email: ibragwork@gmail.com
License: APACHE 2.0
Platform: UNKNOWN
